[
  { "timestamp": "2026-03-27T02:45:00.000Z", "open": 22218, "high": 22230, "low": 22206, "close": 22224, "volume": 88200 },
  { "timestamp": "2026-03-27T02:50:00.000Z", "open": 22224, "high": 22236, "low": 22218, "close": 22231, "volume": 89600 },
  { "timestamp": "2026-03-27T02:55:00.000Z", "open": 22231, "high": 22242, "low": 22225, "close": 22238, "volume": 91400 },
  { "timestamp": "2026-03-27T03:00:00.000Z", "open": 22238, "high": 22252, "low": 22234, "close": 22248, "volume": 93200 },
  { "timestamp": "2026-03-27T03:05:00.000Z", "open": 22248, "high": 22263, "low": 22244, "close": 22258, "volume": 96500 },
  { "timestamp": "2026-03-27T03:10:00.000Z", "open": 22258, "high": 22276, "low": 22252, "close": 22271, "volume": 98800 },
  { "timestamp": "2026-03-27T03:15:00.000Z", "open": 22271, "high": 22290, "low": 22266, "close": 22284, "volume": 101400 },
  { "timestamp": "2026-03-27T03:20:00.000Z", "open": 22284, "high": 22298, "low": 22279, "close": 22292, "volume": 103200 },
  { "timestamp": "2026-03-27T03:25:00.000Z", "open": 22292, "high": 22304, "low": 22286, "close": 22299, "volume": 105600 },
  { "timestamp": "2026-03-27T03:30:00.000Z", "open": 22299, "high": 22312, "low": 22294, "close": 22306, "volume": 109100 },
  { "timestamp": "2026-03-27T03:35:00.000Z", "open": 22306, "high": 22318, "low": 22300, "close": 22312, "volume": 113400 },
  { "timestamp": "2026-03-27T03:40:00.000Z", "open": 22312, "high": 22322, "low": 22305, "close": 22310, "volume": 116700 },
  { "timestamp": "2026-03-27T03:45:00.000Z", "open": 22310, "high": 22324, "low": 22298, "close": 22320, "volume": 118000 },
  { "timestamp": "2026-03-27T03:50:00.000Z", "open": 22320, "high": 22336, "low": 22314, "close": 22328, "volume": 121500 },
  { "timestamp": "2026-03-27T03:55:00.000Z", "open": 22328, "high": 22341, "low": 22322, "close": 22338, "volume": 124200 },
  { "timestamp": "2026-03-27T04:00:00.000Z", "open": 22338, "high": 22345, "low": 22330, "close": 22334, "volume": 110800 },
  { "timestamp": "2026-03-27T04:05:00.000Z", "open": 22334, "high": 22352, "low": 22329, "close": 22348, "volume": 136400 },
  { "timestamp": "2026-03-27T04:10:00.000Z", "open": 22348, "high": 22360, "low": 22342, "close": 22358, "volume": 140100 },
  { "timestamp": "2026-03-27T04:15:00.000Z", "open": 22358, "high": 22368, "low": 22350, "close": 22361, "volume": 138700 },
  { "timestamp": "2026-03-27T04:20:00.000Z", "open": 22361, "high": 22366, "low": 22351, "close": 22356, "volume": 129500 },
  { "timestamp": "2026-03-27T04:25:00.000Z", "open": 22356, "high": 22372, "low": 22355, "close": 22369, "volume": 151300 },
  { "timestamp": "2026-03-27T04:30:00.000Z", "open": 22369, "high": 22379, "low": 22360, "close": 22375, "volume": 160800 },
  { "timestamp": "2026-03-27T04:35:00.000Z", "open": 22375, "high": 22386, "low": 22368, "close": 22382, "volume": 157600 },
  { "timestamp": "2026-03-27T04:40:00.000Z", "open": 22382, "high": 22390, "low": 22374, "close": 22388, "volume": 166900 },
  { "timestamp": "2026-03-27T04:45:00.000Z", "open": 22388, "high": 22395, "low": 22380, "close": 22392, "volume": 170500 },
  { "timestamp": "2026-03-27T04:50:00.000Z", "open": 22392, "high": 22404, "low": 22388, "close": 22399, "volume": 181400 },
  { "timestamp": "2026-03-27T04:55:00.000Z", "open": 22399, "high": 22410, "low": 22394, "close": 22406, "volume": 190300 },
  { "timestamp": "2026-03-27T05:00:00.000Z", "open": 22406, "high": 22415, "low": 22400, "close": 22411, "volume": 198100 },
  { "timestamp": "2026-03-27T05:05:00.000Z", "open": 22411, "high": 22424, "low": 22408, "close": 22418, "volume": 206500 },
  { "timestamp": "2026-03-27T05:10:00.000Z", "open": 22418, "high": 22432, "low": 22414, "close": 22427, "volume": 214600 },
  { "timestamp": "2026-03-27T05:15:00.000Z", "open": 22427, "high": 22439, "low": 22420, "close": 22434, "volume": 221900 },
  { "timestamp": "2026-03-27T05:20:00.000Z", "open": 22434, "high": 22448, "low": 22428, "close": 22445, "volume": 233700 }
]
